network.py
setup.py
network.egg-info/PKG-INFO
network.egg-info/SOURCES.txt
network.egg-info/dependency_links.txt
network.egg-info/not-zip-safe
network.egg-info/top_level.txt