Metadata-Version: 1.0
Name: network
Version: 0.1
Summary: A very simple networking library written by David Whale (@whaleygeek).
Home-page: https://www.raspberrypi.org/learning/networking-lessons/
Author: Andrew Mulholland
Author-email: gbaman@users.noreply.github.com
License: MIT
Platform: UNKNOWN
